polars_candle-0.1.7.dist-info/METADATA
polars_candle-0.1.7.dist-info/WHEEL
polars_candle/candle_ext.py
polars_candle/__init__.py
polars_candle/polars_candle.cpython-39-x86_64-linux-gnu.so
polars_candle-0.1.7.dist-info/RECORD
