Metadata-Version: 2.3
Name: polars_candle
Version: 0.1.7
Classifier: Programming Language :: Rust
Classifier: Programming Language :: Python :: Implementation :: CPython
Classifier: Programming Language :: Python :: Implementation :: PyPy
Summary: A text embedding extension for the Polars Dataframe library.
Keywords: polars,dataframe,embedding,nlp,candle
Author: Wouter Doppenberg <wouterdoppenberg@gmail.com>
Author-email: Wouter Doppenberg <wouterdoppenberg@gmail.com>
License: Apache-2.0
Requires-Python: >=3.9
Project-URL: repository, https://github.com/wdoppenberg/polars-candle
